zero_leak/__init__.py
zero_leak/cli.py
zero_leak/ghost.py
zero_leak/mirage.py
zero_leak/shield.py
zero_leak-1.0.0.dist-info/METADATA
zero_leak-1.0.0.dist-info/WHEEL
zero_leak-1.0.0.dist-info/entry_points.txt
zero_leak-1.0.0.dist-info/RECORD
