Metadata-Version: 2.4
Name: zero-leak
Version: 1.0.0
Summary: Three-layer defense system against secret-stealing bots. Pre-commit hooks, honeypot generators, and MEV rescue.
Project-URL: Homepage, https://github.com/Patrickschell609/zero-leak
Project-URL: Repository, https://github.com/Patrickschell609/zero-leak
Project-URL: Issues, https://github.com/Patrickschell609/zero-leak/issues
Author-email: Patrick Schell <patrickschell609@gmail.com>
License-Expression: MIT
Keywords: crypto,ethereum,flashbots,git,honeypot,mev,pre-commit,protection,secrets,security,wallet
Classifier: Development Status :: 5 - Production/Stable
Classifier: Environment :: Console
Classifier: Intended Audience :: Developers
Classifier: License :: OSI Approved :: MIT License
Classifier: Operating System :: OS Independent
Classifier: Programming Language :: Python :: 3
Classifier: Programming Language :: Python :: 3.8
Classifier: Programming Language :: Python :: 3.9
Classifier: Programming Language :: Python :: 3.10
Classifier: Programming Language :: Python :: 3.11
Classifier: Programming Language :: Python :: 3.12
Classifier: Topic :: Security
Classifier: Topic :: Software Development :: Version Control :: Git
Requires-Python: >=3.8
Requires-Dist: eth-account>=0.9.0
Requires-Dist: requests>=2.28.0
Requires-Dist: web3>=6.0.0
Provides-Extra: dev
Requires-Dist: black>=23.0.0; extra == 'dev'
Requires-Dist: pytest>=7.0.0; extra == 'dev'
